jordan_py/__init__.py
jordan_py/jordan.py
jordan_py/test/__init__.py
jordan_py/test/test_jordan.py
jordan_py-1.0.0.dist-info/LICENSE
jordan_py-1.0.0.dist-info/METADATA
jordan_py-1.0.0.dist-info/WHEEL
jordan_py-1.0.0.dist-info/top_level.txt
jordan_py-1.0.0.dist-info/RECORD
