Metadata-Version: 2.1
Name: jordan-py
Version: 1.0.0
Summary: A Python library easing use of Jordan in your Python code.
Home-page: https://github.com/Mara-tech/jordan
Author: Pierrick Baudet
Author-email: pbaudet.enseirb@gmail.com
License: MIT License (see LICENSE.txt)
Platform: UNKNOWN
Requires-Dist: requests
